{
  "_meta": {
    "description": "Latest UK IT job market snapshot for a curated set of technology skills. Data sourced from IT Jobs Watch (itjobswatch.co.uk), which aggregates permanent job listings across the UK. Scraped weekly via GitHub Actions.",
    "snapshot_date": "2026-05-03",
    "data_source": "IT Jobs Watch (itjobswatch.co.uk)",
    "market": "United Kingdom — permanent roles only",
    "period": "6mo",
    "period_explanation": "All count and rank fields use a rolling 6-month window ending on snapshot_date. This means 'total_postings' is the cumulative number of distinct job postings referencing the skill over those six months — it is NOT a monthly average or a point-in-time count.",
    "companion_file": "latest_3mo.json",
    "caveats": [
      "demand_rank is relative to ALL IT skills tracked by IT Jobs Watch, not just the skills listed in this file. A rank of 5 means 5th most in-demand across the entire UK IT job market.",
      "live_jobs is a point-in-time count of active listings at the moment of scraping. It will typically be much lower than total_postings.",
      "market_share_pct is this skill's share of ALL permanent UK IT roles over the window, not just the skills in this file. Values will not sum to 100%.",
      "demand_rank_yoy_change is sign-flipped relative to the raw rank number: a POSITIVE value means the rank NUMBER went down (i.e. the skill became MORE in demand). A NEGATIVE value means it became less in demand.",
      "null values indicate the source site did not report a figure for that field.",
      "This file tracks a curated subset of skills. Absence from this list does not imply low demand."
    ],
    "field_definitions": {
      "skill": "Technology or domain name.",
      "demand_rank": "Demand rank among all IT skills on IT Jobs Watch. Lower number = higher demand. Rank 1 = most in-demand skill in the UK IT market.",
      "demand_rank_yoy_change": "Change in demand rank versus the same window one year ago. Positive = skill became more in demand (rank number fell). Negative = skill became less in demand (rank number rose).",
      "live_jobs": "Active job listings at the moment of scraping (point-in-time).",
      "total_postings": "Cumulative count of job postings referencing this skill over the rolling window. Not an average — this is the total.",
      "market_share_pct": "Percentage of all permanent UK IT job postings (not just tracked skills) that reference this skill, over the rolling window.",
      "median_salary_gbp": "Median advertised annual salary in GBP for roles requiring this skill.",
      "median_salary_yoy_change_pct": "Year-over-year percentage change in median salary. Positive = salaries rose. Negative = salaries fell."
    }
  },
  "skills": {
    "Language": [
      {
        "skill": "Python",
        "demand_rank": 14,
        "demand_rank_yoy_change": null,
        "live_jobs": 2951,
        "total_postings": 6666,
        "market_share_pct": 7.4,
        "median_salary_gbp": 67500,
        "median_salary_yoy_change_pct": -10.0
      },
      {
        "skill": "SQL",
        "demand_rank": 21,
        "demand_rank_yoy_change": null,
        "live_jobs": 2345,
        "total_postings": 5671,
        "market_share_pct": 6.3,
        "median_salary_gbp": 60000,
        "median_salary_yoy_change_pct": null
      },
      {
        "skill": "Java",
        "demand_rank": 72,
        "demand_rank_yoy_change": null,
        "live_jobs": 780,
        "total_postings": 2375,
        "market_share_pct": 2.64,
        "median_salary_gbp": 72500,
        "median_salary_yoy_change_pct": -3.33
      },
      {
        "skill": "JavaScript",
        "demand_rank": 77,
        "demand_rank_yoy_change": null,
        "live_jobs": 893,
        "total_postings": 2126,
        "market_share_pct": 2.36,
        "median_salary_gbp": 59773,
        "median_salary_yoy_change_pct": -8.04
      },
      {
        "skill": "R",
        "demand_rank": 442,
        "demand_rank_yoy_change": null,
        "live_jobs": 162,
        "total_postings": 280,
        "market_share_pct": 0.31,
        "median_salary_gbp": 31500,
        "median_salary_yoy_change_pct": -49.19
      }
    ],
    "Cloud Platform": [
      {
        "skill": "Azure",
        "demand_rank": 2,
        "demand_rank_yoy_change": null,
        "live_jobs": 3465,
        "total_postings": 11907,
        "market_share_pct": 13.22,
        "median_salary_gbp": 65000,
        "median_salary_yoy_change_pct": 4.0
      },
      {
        "skill": "AWS",
        "demand_rank": 24,
        "demand_rank_yoy_change": null,
        "live_jobs": 2417,
        "total_postings": 5395,
        "market_share_pct": 5.99,
        "median_salary_gbp": 72500,
        "median_salary_yoy_change_pct": null
      },
      {
        "skill": "Databricks",
        "demand_rank": 216,
        "demand_rank_yoy_change": null,
        "live_jobs": 387,
        "total_postings": 813,
        "market_share_pct": 0.9,
        "median_salary_gbp": 85000,
        "median_salary_yoy_change_pct": 6.25
      },
      {
        "skill": "Snowflake",
        "demand_rank": 319,
        "demand_rank_yoy_change": null,
        "live_jobs": 227,
        "total_postings": 476,
        "market_share_pct": 0.53,
        "median_salary_gbp": 85000,
        "median_salary_yoy_change_pct": -8.1
      }
    ],
    "Domain": [
      {
        "skill": "AI",
        "demand_rank": 6,
        "demand_rank_yoy_change": null,
        "live_jobs": 3830,
        "total_postings": 10752,
        "market_share_pct": 11.94,
        "median_salary_gbp": 70000,
        "median_salary_yoy_change_pct": null
      },
      {
        "skill": "Cybersecurity",
        "demand_rank": 7,
        "demand_rank_yoy_change": null,
        "live_jobs": 1641,
        "total_postings": 10325,
        "market_share_pct": 11.47,
        "median_salary_gbp": 55000,
        "median_salary_yoy_change_pct": -8.33
      },
      {
        "skill": "Software Engineering",
        "demand_rank": 17,
        "demand_rank_yoy_change": null,
        "live_jobs": 1987,
        "total_postings": 5919,
        "market_share_pct": 6.57,
        "median_salary_gbp": 70000,
        "median_salary_yoy_change_pct": -3.44
      },
      {
        "skill": "Data Science",
        "demand_rank": 150,
        "demand_rank_yoy_change": null,
        "live_jobs": 828,
        "total_postings": 1165,
        "market_share_pct": 1.29,
        "median_salary_gbp": 70000,
        "median_salary_yoy_change_pct": null
      }
    ]
  }
}